wbBase/__init__.py
wbBase/application.py
wbBase/applicationInfo.py
wbBase/applicationWindow.py
wbBase/artprovider.py
wbBase/panelManager.py
wbBase/pluginManager.py
wbBase/py.typed
wbBase/scripting.py
wbBase/shortcut.py
wbBase/tools.py
wbBase/control/__init__.py
wbBase/control/externalToolConfig.py
wbBase/control/externalToolConfigUI.py
wbBase/control/filling.py
wbBase/control/iePanel.py
wbBase/control/propgrid.py
wbBase/control/textEditControl.py
wbBase/dialog/__init__.py
wbBase/dialog/multiSaveModifiedDialog.py
wbBase/dialog/multiSaveModifiedDialogUI.py
wbBase/dialog/preferences.py
wbBase/document/__init__.py
wbBase/document/manager.py
wbBase/document/notebook.py
wbBase/document/template.py
wbBase/document/view.py
wbbase-0.2.13.dist-info/licenses/LICENSE
wbbase-0.2.13.dist-info/METADATA
wbbase-0.2.13.dist-info/WHEEL
wbbase-0.2.13.dist-info/top_level.txt
wbbase-0.2.13.dist-info/RECORD
