Metadata-Version: 2.4
Name: wbBase
Version: 0.2.13
Summary: Base package for WorkBench applications.
Author: Andreas Eigendorf
License-Expression: MIT
Keywords: workbench,wxPython,GUI
Platform: WIN32
Platform: WIN64
Platform: OSX
Platform: POSIX
Classifier: Development Status :: 4 - Beta
Classifier: Operating System :: MacOS
Classifier: Operating System :: Microsoft :: Windows
Classifier: Operating System :: POSIX
Classifier: Environment :: MacOS X :: Cocoa
Classifier: Environment :: Win32 (MS Windows)
Classifier: Environment :: X11 Applications :: GTK
Classifier: Programming Language :: Python :: 3
Classifier: Programming Language :: Python :: 3.8
Classifier: Programming Language :: Python :: 3.9
Classifier: Programming Language :: Python :: 3.10
Classifier: Programming Language :: Python :: 3.11
Classifier: Programming Language :: Python :: 3.12
Classifier: Programming Language :: Python :: Implementation :: CPython
Classifier: Intended Audience :: Developers
Classifier: Topic :: Software Development :: Libraries
Classifier: Topic :: Software Development :: User Interfaces
Requires-Python: >=3.8
License-File: LICENSE
Requires-Dist: wxpython>=4.2.3
Requires-Dist: GitPython>=3.1
Requires-Dist: PyYAML>=6.0
Requires-Dist: importlib_metadata; python_version < "3.10"
Dynamic: license-file
